random_password_generator/__init__.py
random_password_generator/rpg.py
random_password_generator/messages/__init__.py
random_password_generator_cli-1.0.2.dist-info/LICENSE
random_password_generator_cli-1.0.2.dist-info/METADATA
random_password_generator_cli-1.0.2.dist-info/WHEEL
random_password_generator_cli-1.0.2.dist-info/entry_points.txt
random_password_generator_cli-1.0.2.dist-info/top_level.txt
random_password_generator_cli-1.0.2.dist-info/RECORD
