Metadata-Version: 2.1
Name: random-password-generator-cli
Version: 1.0.2
Summary: Command line tool utility to generate random entropic password
Home-page: https://github.com/Leovalcante/random-password-generator
Author: Valerio Preti
Author-email: valerio.preti.rpg@gmail.com
License: MIT
Platform: UNKNOWN
Classifier: Environment :: Console
Classifier: Intended Audience :: End Users/Desktop
Classifier: License :: OSI Approved :: MIT License
Classifier: Operating System :: OS Independent
Classifier: Programming Language :: Python :: 3
Requires-Python: >=3.7
Requires-Dist: click (>=7.0)
Requires-Dist: requests (>=2.0)
